uritools/__init__.py
uritools/chars.py
uritools/classify.py
uritools/compose.py
uritools/defrag.py
uritools/encoding.py
uritools/join.py
uritools/split.py
uritools-3.0.2.dist-info/LICENSE
uritools-3.0.2.dist-info/METADATA
uritools-3.0.2.dist-info/WHEEL
uritools-3.0.2.dist-info/top_level.txt
uritools-3.0.2.dist-info/RECORD
